<?xml version="1.0" encoding="UTF-8" ?>
<Configuration>
  <WagstaffCurrdata>
    <!--Настройка тегов для текущих данных при активном процессе плавки-->
    <!--Интервал времени, через который будет происходить считывание данных в миллисекундах-->
    <ReadInterval>5000</ReadInterval>
    <Data>
      <Item>
        <OpcItemName>[MOSSNER2]L3_Interface.IN.LiveBit</OpcItemName>
        <TypeName>mixer</TypeName>
        <ObjectName>mixer1</ObjectName>
        <DataName>temperatura</DataName>
      </Item>
      <Item>
        <OpcItemName>[MOSSNER2]L3_Interface.OUT.LiveBit</OpcItemName>
        <TypeName>mixer</TypeName>
        <ObjectName>mixer1</ObjectName>
        <DataName>temperatura</DataName>
      </Item>
    </Data>
  </WagstaffCurrdata>
  <MixerCurdata>
    <!--Настройка тегов для миксеров-->
    <!--Интервал времени, через который будет происходить считывание данных в миллисекундах-->
    <ReadInterval>5000</ReadInterval>
    <Data>
      <Item>
        <OpcItemName>[MOSSNER2]L3_Interface.IN.LiveBit</OpcItemName>
        <TypeName>mixer</TypeName>
        <ObjectName>mixer1</ObjectName>
        <DataName>temperatura</DataName>
      </Item>
    </Data>
  </MixerCurdata>
</Configuration>